tanabesugano/__init__.py
tanabesugano/batch.py
tanabesugano/cmd.py
tanabesugano/constants.py
tanabesugano/matrices.py
tanabesugano/tools.py
tanabesugano/test/__init__.py
tanabesugano/test/test_batch.py
tanabesugano/test/test_front.py
tanabesugano/test/test_matrices.py
tanabesugano/test/test_num.py
tanabesugano-1.6.1.dist-info/METADATA
tanabesugano-1.6.1.dist-info/WHEEL
tanabesugano-1.6.1.dist-info/entry_points.txt
tanabesugano-1.6.1.dist-info/licenses/LICENSE
tanabesugano-1.6.1.dist-info/RECORD
