Metadata-Version: 2.4
Name: tanabesugano
Version: 1.6.1
Summary: A python-solver for Tanabe-Sugano and Energy-Correlation diagrams
Project-URL: Homepage, https://pypi.org/project/TanabeSugano
Project-URL: Repository, https://github.com/Anselmoo/TanabeSugano
Author-email: Anselm Hahn <anselm.hahn@gmail.com>
Maintainer-email: Anselm Hahn <anselm.hahn@gmail.com>
License: MIT
License-File: LICENSE
Keywords: complex-ions,data-visualization,energy-correlation,tanabe-sugano,terminal
Classifier: Development Status :: 5 - Production/Stable
Classifier: Environment :: Console
Classifier: Intended Audience :: Education
Classifier: Intended Audience :: Science/Research
Classifier: License :: OSI Approved :: MIT License
Classifier: Operating System :: MacOS
Classifier: Operating System :: Microsoft :: Windows
Classifier: Operating System :: Unix
Classifier: Programming Language :: Python :: 3
Classifier: Programming Language :: Python :: 3.10
Classifier: Programming Language :: Python :: 3.11
Classifier: Programming Language :: Python :: 3.12
Classifier: Programming Language :: Python :: 3.13
Classifier: Programming Language :: Python :: 3.14
Classifier: Topic :: Scientific/Engineering :: Chemistry
Classifier: Topic :: Scientific/Engineering :: Physics
Classifier: Topic :: Scientific/Engineering :: Visualization
Classifier: Topic :: System :: Shells
Classifier: Topic :: Utilities
Requires-Python: >=3.10
Requires-Dist: matplotlib>=3.4.2
Requires-Dist: numpy<2.0,>=1.26.4; python_version == '3.10'
Requires-Dist: numpy>=2.0.2; python_version >= '3.11'
Requires-Dist: pandas<4.0.0,>=1.2.4
Requires-Dist: prettytable<4.0,>=2.1
Requires-Dist: update<1.0.0,>=0.0.1
Provides-Extra: plotly
Requires-Dist: plotly<7.0.0,>=5.13.1; extra == 'plotly'
